Lab 2/CSE3100_Lab2_PartD/CircuitD.v
module POS(X1, X2, X3, F); // Created module which is the Product of Sum Form 
    
    input X1, X2, X3; // Created input variables X1, X2, X3
    output F; // output variable called F 

    assign F = (1&!X2&X3 | X1&1&!X3); // Synthesized Product of sum form 

endmodule

module minimizedForm(X1, X2, X3, F); // Created module for minimized form 

    input X1, X2, X3; // Created input variables X1, X2, X3
    output F; // output variable called F 

    assign F = (!X2&X3 | X1&!X3); // Synthesized of minimized form 

endmodule

Lab 2/CSE3100_Lab2_PartD/CircuitD_tb.v
`timescale 1ns/1ns  // added timescale 
`include "CircuitD.v" // Included file called CircuitD.v 

module CircuitD_tb; 

    reg A, B, C; // created Registers A, B, C
    wire POSForm_F; // Created wire for product of sum form 
    wire minimizedForm_F; // Created wire for minimizedForm 

    POS uut(A, B, C, POSForm_F); // Declaration of the module POS with instance of uut and passing input and output variable in same order 
    minimizedForm uut2(A, B, C, minimizedForm_F);  // Declaration of the module minimizedForm with instance of uut2 and passing input and output variable in same order 


    initial begin 
        $dumpfile("CircuitD_tb.vcd"); // Saving the waveforms to vcd file 
        $dumpvars(0, CircuitD_tb); 

        // Truth Table with amount time #20 nano seconds 

        A = 0; B = 0; C = 0; #20 
        A = 0; B = 0; C = 1; #20 
        A = 0; B = 1; C = 0; #20 
        A = 0; B = 1; C = 1; #20 
        A = 1; B = 0; C = 0; #20 
        A = 1; B = 0; C = 1; #20 
        A = 1; B = 1; C = 0; #20 
        A = 1; B = 1; C = 1; #20 

        $display("Complete"); // Displays to the terminal that the program ran 

    end 

endmodule

Lab 2/CSE3100_Lab2_PartD/CircuitD_tb.vcd
$date
	Sat Oct  5 15:18:29 2024
$end
$version
	Icarus Verilog
$end
$timescale
	1ns
$end
$scope module CircuitD_tb $end
$var wire 1 ! minimizedForm_F $end
$var wire 1 " POSForm_F $end
$var reg 1 # A $end
$var reg 1 $ B $end
$var reg 1 % C $end
$scope module uut $end
$var wire 1 # X1 $end
$var wire 1 $ X2 $end
$var wire 1 % X3 $end
$var wire 1 " F $end
$upscope $end
$scope module uut2 $end
$var wire 1 ! F $end
$var wire 1 # X1 $end
$var wire 1 $ X2 $end
$var wire 1 % X3 $end
$upscope $end
$upscope $end
$enddefinitions $end
$comment Show the parameter values. $end
$dumpall
$end
#0
$dumpvars
0%
0$
0#
0"
0!
$end
#20
1"
1!
1%
#40
0"
0!
0%
1$
#60
1%
#80
1"
1!
0%
0$
1#
#100
1%
#120
0%
1$
#140
0"
0!
1%
