Lab 4/Lab4a/fullAdder.v
module halfAdder(op1, op2, sum, carry); // Module for half adder

    input op1, op2; 
    output sum, carry; 

    assign sum = op1 ^ op2; // ^ is the XOR operator  
    assign carry = op1 & op2; // & is the AND operator 

endmodule 

module fullAdder(A, B, carryIn, sum, carryOut); // module for full adder 
    // inputs and ouputs for the full adder 
    input A, B, carryIn; 
    output sum, carryOut; 
    // intermediary wires 
    wire c, d, e; 

    halfAdder u1(A, B, c, d); 
    halfAdder u2(carryIn, c, e, f); 

    assign carryOut = f | d; 
    assign sum = e; 

endmodule

Lab 4/Lab4a/fullAdder_tb.v
`timescale 1ns / 1ns 
`include "fullAdder.v" 

module fullAdder_tb; 

    reg A, B, carryIn; 
    wire sum, carryOut; 

    fullAdder uut(A, B, carryIn, sum, carryOut); 

initial begin   

    $dumpfile("fullAdder_tb.vcd"); 
    $dumpvars(0, fullAdder_tb); 

    {A, B, carryIn} = 3'd0; #20;
    {A, B, carryIn} = 3'd1; #20;
    {A, B, carryIn} = 3'd2; #20;
    {A, B, carryIn} = 3'd3; #20;
    {A, B, carryIn} = 3'd4; #20;
    {A, B, carryIn} = 3'd5; #20;
    {A, B, carryIn} = 3'd6; #20;
    {A, B, carryIn} = 3'd7; #20;

    $display("Finished additions!"); 

end 

endmodule

Lab 4/Lab4a/fullAdder_tb.vcd
$date
	Fri Nov 22 21:43:11 2024
$end
$version
	Icarus Verilog
$end
$timescale
	1ns
$end
$scope module fullAdder_tb $end
$var wire 1 ! sum $end
$var wire 1 " carryOut $end
$var reg 1 # A $end
$var reg 1 $ B $end
$var reg 1 % carryIn $end
$scope module uut $end
$var wire 1 # A $end
$var wire 1 $ B $end
$var wire 1 % carryIn $end
$var wire 1 " carryOut $end
$var wire 1 ! sum $end
$var wire 1 & f $end
$var wire 1 ' e $end
$var wire 1 ( d $end
$var wire 1 ) c $end
$scope module u1 $end
$var wire 1 ( carry $end
$var wire 1 # op1 $end
$var wire 1 $ op2 $end
$var wire 1 ) sum $end
$upscope $end
$scope module u2 $end
$var wire 1 & carry $end
$var wire 1 % op1 $end
$var wire 1 ) op2 $end
$var wire 1 ' sum $end
$upscope $end
$upscope $end
$upscope $end
$enddefinitions $end
$comment Show the parameter values. $end
$dumpall
$end
#0
$dumpvars
0)
0(
0'
0&
0%
0$
0#
0"
0!
$end
#20
1!
1'
1%
#40
1)
1!
1'
1$
0%
#60
1"
0!
0'
1&
1%
#80
0"
1!
1'
0&
1#
0$
0%
#100
1"
0!
0'
1&
1%
#120
0)
1(
0!
0'
0&
1$
0%
#140
1!
1'
1%
