Lab 4/Lab4b/fullSubtractor.v
module halfSubtractor(op1, op2, diff, borrow);

    input op1, op2; 
    output diff, borrow; 

    assign diff = op1 ^ op2; // op1 xor op2
    assign borrow = !op1 & op2; // not op1 AND op2 
 
endmodule 

module fullSubtractor(A, B, borrowIn, diff, borrowOut);

    input A, B, borrowIn; 
    output diff, borrowOut; 

    wire c, d, e, f; // all the wires ulitized 

    halfSubtractor u1(A, B, c, d);
    halfSubtractor u2(c, borrowIn, e, f); // c is first instead of borrowIn because working on fullSubtractor not fullAdder 

    assign borrowOut = f | d; 
    assign diff = e; 
 
endmodule

Lab 4/Lab4b/fullSubtractor_tb.v
`timescale 1ns / 1ns 
`include "fullSubtractor.v" 

module fullSubtractor_tb; 

    reg A, B, borrowIn; // created reg for A , B, borrowIn 
    wire diff, borrowOut; 

    fullSubtractor uut(A, B, borrowIn, diff, borrowOut); // uut is "unit under test" 

initial begin 

    $dumpfile("fullSubtractor_tb.vcd"); 
    $dumpvars(0, fullSubtractor_tb); 

    {A, B, borrowIn} = 3'd0; #20; // Short handed way of sending inputs 
    {A, B, borrowIn} = 3'd1; #20; // Treat the 3 one bit binary numbers as a 3 bit binary number 
    {A, B, borrowIn} = 3'd2; #20; // 3'd2 is the 3 binary number that equals 2 base 10 
    {A, B, borrowIn} = 3'd3; #20; // Also waited 20 nano seconds 
    {A, B, borrowIn} = 3'd4; #20;
    {A, B, borrowIn} = 3'd5; #20;
    {A, B, borrowIn} = 3'd6; #20;
    {A, B, borrowIn} = 3'd7; #20;

    $display("Finished subtractions!"); // display once finished 

end 

endmodule

Lab 4/Lab4b/fullSubtractor_tb.vcd
$date
	Wed Nov 27 17:57:07 2024
$end
$version
	Icarus Verilog
$end
$timescale
	1ns
$end
$scope module fullSubtractor_tb $end
$var wire 1 ! diff $end
$var wire 1 " borrowOut $end
$var reg 1 # A $end
$var reg 1 $ B $end
$var reg 1 % borrowIn $end
$scope module uut $end
$var wire 1 # A $end
$var wire 1 $ B $end
$var wire 1 % borrowIn $end
$var wire 1 " borrowOut $end
$var wire 1 ! diff $end
$var wire 1 & f $end
$var wire 1 ' e $end
$var wire 1 ( d $end
$var wire 1 ) c $end
$scope module u1 $end
$var wire 1 ( borrow $end
$var wire 1 ) diff $end
$var wire 1 # op1 $end
$var wire 1 $ op2 $end
$upscope $end
$scope module u2 $end
$var wire 1 & borrow $end
$var wire 1 ' diff $end
$var wire 1 ) op1 $end
$var wire 1 % op2 $end
$upscope $end
$upscope $end
$upscope $end
$enddefinitions $end
$comment Show the parameter values. $end
$dumpall
$end
#0
$dumpvars
0)
0(
0'
0&
0%
0$
0#
0"
0!
$end
#20
1"
1!
1'
1&
1%
#40
1)
1(
1!
1'
0&
1$
0%
#60
0!
0'
1%
#80
0"
0(
1!
1'
1#
0$
0%
#100
0!
0'
1%
#120
0)
0!
0'
1$
0%
#140
1"
1!
1'
1&
1%
